diaml/__init__.py
diaml/imputer.py
diaml/transformations.py
diaml-1.1.0a1.dist-info/DESCRIPTION.rst
diaml-1.1.0a1.dist-info/METADATA
diaml-1.1.0a1.dist-info/RECORD
diaml-1.1.0a1.dist-info/WHEEL
diaml-1.1.0a1.dist-info/metadata.json
diaml-1.1.0a1.dist-info/top_level.txt
