Metadata-Version: 2.0
Name: diaml
Version: 1.1.0a1
Summary: Does It All Machine Learning
Home-page: http://github.com/chasedehan/diaml
Author: Chase DeHan
Author-email: chasedehan@yahoo.com
License: MIT
Platform: UNKNOWN
Requires-Dist: numpy
Requires-Dist: pandas
Requires-Dist: sklearn
